LICENSE
MANIFEST.in
README
README.md
setup.cfg
setup.py
pyiArduinoI2Cph/__init__.py
pyiArduinoI2Cph/iarduino_I2C_PI.cpp
pyiArduinoI2Cph/iarduino_I2C_PI.h
pyiArduinoI2Cph/iarduino_I2C_pH.cpp
pyiArduinoI2Cph/iarduino_I2C_pH.h
pyiArduinoI2Cph/iarduino_I2C_pH.pxd
pyiArduinoI2Cph/pyiArduinoI2Cph.cpp
pyiArduinoI2Cph/pyiArduinoI2Cph.pyx
pyiArduinoI2Cph/setup.py
pyiArduinoI2Cph.egg-info/PKG-INFO
pyiArduinoI2Cph.egg-info/SOURCES.txt
pyiArduinoI2Cph.egg-info/dependency_links.txt
pyiArduinoI2Cph.egg-info/top_level.txt
pyiArduinoI2Cph/cpp/FindDevices.cpp
pyiArduinoI2Cph/cpp/NewAddress.cpp
pyiArduinoI2Cph/cpp/Serial.h
pyiArduinoI2Cph/cpp/getData.cpp
pyiArduinoI2Cph/cpp/getFunction.cpp
pyiArduinoI2Cph/cpp/getSettings.cpp
pyiArduinoI2Cph/examples/FindDevices.py
pyiArduinoI2Cph/examples/getData.py
pyiArduinoI2Cph/examples/getFunction.py
pyiArduinoI2Cph/examples/getSettings.py
pyiArduinoI2Cph/examples/newAddress.py
pyiArduinoI2Cph/examples/setCalibration.py
pyiArduinoI2Cph/examples/setSettings.py