Metadata-Version: 2.1
Name: pyiArduinoI2Cph
Version: 1.2.3
Summary: iarduino.ru module for Raspberry Pi
Home-page: http://github.com/tremaru/pyiArduinoI2Cph
Author: iarduino.ru
Author-email: shop@iarduino.ru
License: MIT
Classifier: Programming Language :: Python :: 3
License-File: LICENSE
